examples/test_build123d hexapod.py
examples/test_cache.py
examples/test_cadquery_bearing.py
examples/test_cadquery_disk-arm.py
examples/test_cadquery_jansen-linkage.py
examples/test_cadquery_sketch.py
examples/test_color.py
examples/test_coordsystem.py
examples/test_instances.py
examples/test_stl.py
examples/tests_build123d assembly.py
examples/tests_build123d hinge.py
examples/tests_build123d.py
examples/tests_cadquery.py
examples/tests_cadquery_boxes.py
examples/tests_cadquery_door.py
examples/tests_cadquery_hexapod.py
ocp_tessellate/__init__.py
ocp_tessellate/_version.py
ocp_tessellate/cad_objects.py
ocp_tessellate/convert.py
ocp_tessellate/defaults.py
ocp_tessellate/ocp_utils.py
ocp_tessellate/stepreader.py
ocp_tessellate/tessellator.py
ocp_tessellate/trace.py
ocp_tessellate/types.py
ocp_tessellate/utils.py
ocp_tessellate-3.1.2.dist-info/licenses/LICENSE
tests/test_build123d.py
tests/test_cache.py
tests/test_cadquery.py
tests/test_color.py
tests/test_empty.py
tests/test_imageface.py
tests/test_instances.py
ocp_tessellate-3.1.2.dist-info/METADATA
ocp_tessellate-3.1.2.dist-info/WHEEL
ocp_tessellate-3.1.2.dist-info/top_level.txt
ocp_tessellate-3.1.2.dist-info/RECORD
