Metadata-Version: 2.4
Name: ocp-tessellate
Version: 3.1.2
Summary: Tessellate OCP (https://github.com/cadquery/OCP) objects to use with threejs
Author-email: Bernhard Walter <b_walter@arcor.de>
License-Expression: Apache-2.0
Project-URL: Homepage, https://github.com/bernhard-42/ocp-tessellate
Project-URL: Bug Tracker, https://github.com/bernhard-42/ocp-tessellate/issues
Keywords: 3d models,3d printing,3d viewing,3d,brep,cad,cadquery,opencscade,python
Classifier: Operating System :: OS Independent
Classifier: Programming Language :: Python :: 3
Requires-Python: >=3.10
License-File: LICENSE
Requires-Dist: webcolors~=24.8.0
Requires-Dist: numpy
Requires-Dist: cachetools~=5.5.0
Requires-Dist: imagesize
Provides-Extra: dev
Requires-Dist: questionary~=1.10.0; extra == "dev"
Requires-Dist: bump-my-version; extra == "dev"
Requires-Dist: black; extra == "dev"
Requires-Dist: twine; extra == "dev"
Requires-Dist: pytest; extra == "dev"
Dynamic: license-file
